PDS_Test.srcs/sources_1/new/fir_filter.vhd
library IEEE;
use IEEE.STD_LOGIC_1164.ALL;
use IEEE.STD_LOGIC_ARITH.ALL;
use IEEE.STD_LOGIC_UNSIGNED.ALL;
use IEEE.numeric_std.all;

entity fir_core is
  generic (
    N : positive := 2   -- Tamaño configurable
  );
  Port (
    clk : in STD_LOGIC;           -- Reloj
    rst : in STD_LOGIC;           -- Reset asincrónico
    entrada : in STD_LOGIC_VECTOR(N-1 downto 0);     -- Señal de entrada
    sumando : in STD_LOGIC_VECTOR(N-1 downto 0);     -- Sumando
    coeficiente : in STD_LOGIC_VECTOR(N-1 downto 0); -- Coeficiente
    salida : out STD_LOGIC_VECTOR(N-1 downto 0);      -- Salida del componente
    salida_sin_delay : out STD_LOGIC_VECTOR(N-1 downto 0)      -- Salida del componente
  );
end fir_core;

architecture Behavioral of fir_core is
  signal multiplicacion1 : STD_LOGIC_VECTOR(2 * N - 1 downto 0);
  signal suma : STD_LOGIC_VECTOR(N - 1 downto 0);
  signal resultado : STD_LOGIC_VECTOR(N-1 downto 0);
  signal flipflop_salida : STD_LOGIC_VECTOR(N-1 downto 0) := (others => '0');
begin
  -- Multiplicación 1
  multiplicacion1 <= entrada * coeficiente;
  
  -- Multiplicación 2
  suma <= multiplicacion1(2 * N - 1 downto N) + sumando;

  -- Resultado

  resultado <= (others => '0') when rst = '1' else suma;
  
  salida_sin_delay <= resultado;

  -- Flip-flop para almacenar el resultado
  process (clk, rst)
  begin
    if rising_edge(clk) then
      flipflop_salida <= resultado;
    end if;
  end process;
  
  -- Salida del componente
  salida <= flipflop_salida;

end Behavioral;

PDS_Test.srcs/sources_1/new/fir_chain.vhd
--library ieee;
--use ieee.std_logic_1164.all;
--use ieee.numeric_std.all;

--package bus_multiplexer_pkg is
--    constant N : natural := 4;
--    type bus_array is array(natural range <>) of std_logic_vector(N to 0);
--end package;

library ieee;
use ieee.std_logic_1164.all;
use ieee.numeric_std.all;
--use work.bus_multiplexer_pkg.all;

entity filtro_fir_cadena is
  generic
  (
    N : positive := 8; -- Tamaño configurable
    M : positive := 5  -- Número de componentes FIR en la cadena
  );
  port
  (
    clk     : in STD_LOGIC; -- Reloj
    rst     : in STD_LOGIC; -- Reset asincrónico
    entrada : in STD_LOGIC_VECTOR(N - 1 downto 0); -- Señal de entrada común
    coeficientes : in STD_LOGIC_VECTOR(N*M -1 downto 0);
    salida  : out STD_LOGIC_VECTOR(N - 1 downto 0) -- Salida del componente TOP
  );
end filtro_fir_cadena;

architecture Behavioral of filtro_fir_cadena is
  
  
  signal sumando_intermedio : STD_LOGIC_VECTOR(N*(M+1)-1 downto 0) := (others => '0');
  signal salida_sin_delay_s : STD_LOGIC_VECTOR(N*(M+1)-1 downto 0) := (others => '0');
  signal salida_final:        STD_LOGIC_VECTOR(N*M -1 downto 0)    := (others => '0');

  -- Declarar instancias de los componentes FIR
  component fir_core
    generic
    (
       K : positive := N -- Tamaño configurable
    ); 
    port
    (
      clk              : in std_logic;
      rst              : in std_logic;
      entrada          : in std_logic_vector(K - 1 downto 0);
      sumando          : in std_logic_vector(K - 1 downto 0);
      coeficiente      : in std_logic_vector(K - 1 downto 0);
      salida           : out std_logic_vector(K - 1 downto 0);
      salida_sin_delay : out std_logic_vector(K - 1 downto 0)
    );
  end component;

  -- Arreglo de señales de salida sin delay para cada componente FIR


begin
  -- Instancias de los componentes FIR en cadena
  fir_insts: for i in 0 to M - 1 generate
    fir_i: fir_core
      port map(
        clk              => clk,
        rst              => rst,
        entrada          => entrada,
        sumando          => sumando_intermedio((((i+1)*(N))-1) downto i*(N)),
        coeficiente      => coeficientes((((i+1)*(N))-1) downto i*(N)),
        salida           => sumando_intermedio((((i+2)*(N))-1) downto (i+1)*(N)),
        salida_sin_delay => salida_final((((i+1)*(N))-1) downto i*(N))
      );
  end generate;

  -- Salida del componente TOP
  salida <= salida_final(N*M-1 downto N*(M-1));

end Behavioral;

tests/waveforms/cont_dig.vcd
$date
  Sat Dec  2 21:11:16 2023
$end
$version
  GHDL v0
$end
$timescale
  1 fs
$end
$scope module standard $end
$upscope $end
$scope module std_logic_1164 $end
$upscope $end
$scope module numeric_std $end
$upscope $end
$scope module filtro_fir_cadena $end
$var reg 1 ! clk $end
$var reg 1 " rst $end
$var reg 8 # entrada[7:0] $end
$var reg 40 $ coeficientes[39:0] $end
$var reg 8 % salida[7:0] $end
$var reg 48 & sumando_intermedio[47:0] $end
$var reg 48 ' salida_sin_delay_s[47:0] $end
$var reg 40 ( salida_final[39:0] $end
$scope module fir_insts(0) $end
$scope module fir_i $end
$var reg 1 ) clk $end
$var reg 1 * rst $end
$var reg 8 + entrada[7:0] $end
$var reg 8 , sumando[7:0] $end
$var reg 8 - coeficiente[7:0] $end
$var reg 8 . salida[7:0] $end
$var reg 8 / salida_sin_delay[7:0] $end
$var reg 16 0 multiplicacion1[15:0] $end
$var reg 8 1 suma[7:0] $end
$var reg 8 2 resultado[7:0] $end
$var reg 8 3 flipflop_salida[7:0] $end
$upscope $end
$upscope $end
$scope module fir_insts(1) $end
$scope module fir_i $end
$var reg 1 4 clk $end
$var reg 1 5 rst $end
$var reg 8 6 entrada[7:0] $end
$var reg 8 7 sumando[7:0] $end
$var reg 8 8 coeficiente[7:0] $end
$var reg 8 9 salida[7:0] $end
$var reg 8 : salida_sin_delay[7:0] $end
$var reg 16 ; multiplicacion1[15:0] $end
$var reg 8 < suma[7:0] $end
$var reg 8 = resultado[7:0] $end
$var reg 8 > flipflop_salida[7:0] $end
$upscope $end
$upscope $end
$scope module fir_insts(2) $end
$scope module fir_i $end
$var reg 1 ? clk $end
$var reg 1 @ rst $end
$var reg 8 A entrada[7:0] $end
$var reg 8 B sumando[7:0] $end
$var reg 8 C coeficiente[7:0] $end
$var reg 8 D salida[7:0] $end
$var reg 8 E salida_sin_delay[7:0] $end
$var reg 16 F multiplicacion1[15:0] $end
$var reg 8 G suma[7:0] $end
$var reg 8 H resultado[7:0] $end
$var reg 8 I flipflop_salida[7:0] $end
$upscope $end
$upscope $end
$scope module fir_insts(3) $end
$scope module fir_i $end
$var reg 1 J clk $end
$var reg 1 K rst $end
$var reg 8 L entrada[7:0] $end
$var reg 8 M sumando[7:0] $end
$var reg 8 N coeficiente[7:0] $end
$var reg 8 O salida[7:0] $end
$var reg 8 P salida_sin_delay[7:0] $end
$var reg 16 Q multiplicacion1[15:0] $end
$var reg 8 R suma[7:0] $end
$var reg 8 S resultado[7:0] $end
$var reg 8 T flipflop_salida[7:0] $end
$upscope $end
$upscope $end
$scope module fir_insts(4) $end
$scope module fir_i $end
$var reg 1 U clk $end
$var reg 1 V rst $end
$var reg 8 W entrada[7:0] $end
$var reg 8 X sumando[7:0] $end
$var reg 8 Y coeficiente[7:0] $end
$var reg 8 Z salida[7:0] $end
$var reg 8 [ salida_sin_delay[7:0] $end
$var reg 16 \ multiplicacion1[15:0] $end
$var reg 8 ] suma[7:0] $end
$var reg 8 ^ resultado[7:0] $end
$var reg 8 _ flipflop_salida[7:0] $end
$upscope $end
$upscope $end
$upscope $end
$enddefinitions $end
#0
1!
U"
bUUUUUUUU #
b0001100100011001000110010001100100011001 $
bXXXXXXXX %
b000000000000000000000000000000000000000000000000 &
b000000000000000000000000000000000000000000000000 '
bXXXXXXXXXXXXXXXXXXXXXXXXXXXXXXXXXXXXXXXX (
1)
U*
bUUUUUUUU +
b00000000 ,
b00011001 -
b00000000 .
bXXXXXXXX /
bXXXXXXXXXXXXXXXX 0
bXXXXXXXX 1
bXXXXXXXX 2
b00000000 3
14
U5
bUUUUUUUU 6
b00000000 7
b00011001 8
b00000000 9
bXXXXXXXX :
bXXXXXXXXXXXXXXXX ;
bXXXXXXXX <
bXXXXXXXX =
b00000000 >
1?
U@
bUUUUUUUU A
b00000000 B
b00011001 C
b00000000 D
bXXXXXXXX E
bXXXXXXXXXXXXXXXX F
bXXXXXXXX G
bXXXXXXXX H
b00000000 I
1J
UK
bUUUUUUUU L
b00000000 M
b00011001 N
b00000000 O
bXXXXXXXX P
bXXXXXXXXXXXXXXXX Q
bXXXXXXXX R
bXXXXXXXX S
b00000000 T
1U
UV
bUUUUUUUU W
b00000000 X
b00011001 Y
b00000000 Z
bXXXXXXXX [
bXXXXXXXXXXXXXXXX \
bXXXXXXXX ]
bXXXXXXXX ^
b00000000 _
#1000000
0"
b00000000 #
b00000000 %
b0000000000000000000000000000000000000000 (
0*
b00000000 +
b00000000 /
b0000000001000000 0
b00000000 1
b00000000 2
05
b00000000 6
b00000000 :
b0000000001000000 ;
b00000000 <
b00000000 =
0@
b00000000 A
b00000000 E
b0000000001000000 F
b00000000 G
b00000000 H
0K
b00000000 L
b00000000 P
b0000000001000000 Q
b00000000 R
b00000000 S
0V
b00000000 W
b00000000 [
b0000000001000000 \
b00000000 ]
b00000000 ^
#2000000
0!
0)
04
0?
0J
0U
#3000000
#4000000
1!
1)
14
1?
1J
1U
#5000000
#6000000
0!
0)
04
0?
0J
0U
#7000000
b00000001 #
b00000001 +
b0000000001011001 0
b00000001 6
b0000000001011001 ;
b00000001 A
b0000000001011001 F
b00000001 L
b0000000001011001 Q
b00000001 W
b0000000001011001 \
#8000000
1!
1)
14
1?
1J
1U
#9000000
b00000000 #
b00000000 +
b0000000001000000 0
b00000000 6
b0000000001000000 ;
b00000000 A
b0000000001000000 F
b00000000 L
b0000000001000000 Q
b00000000 W
b0000000001000000 \
#10000000
0!
0)
04
0?
0J
0U
#11000000
b00000001 #
b00000001 +
b0000000001011001 0
b00000001 6
b0000000001011001 ;
b00000001 A
b0000000001011001 F
b00000001 L
b0000000001011001 Q
b00000001 W
b0000000001011001 \
#12000000
1!
1)
14
1?
1J
1U
#13000000
b00000000 #
b00000000 +
b0000000001000000 0
b00000000 6
b0000000001000000 ;
b00000000 A
b0000000001000000 F
b00000000 L
b0000000001000000 Q
b00000000 W
b0000000001000000 \
#14000000
0!
0)
04
0?
0J
0U
#15000000
b00000010 #
b00000010 +
b0000000001110010 0
b00000010 6
b0000000001110010 ;
b00000010 A
b0000000001110010 F
b00000010 L
b0000000001110010 Q
b00000010 W
b0000000001110010 \
#16000000
1!
1)
14
1?
1J
1U
#17000000
b00000000 #
b00000000 +
b0000000001000000 0
b00000000 6
b0000000001000000 ;
b00000000 A
b0000000001000000 F
b00000000 L
b0000000001000000 Q
b00000000 W
b0000000001000000 \
#18000000
0!
0)
04
0?
0J
0U
#19000000
b00000010 #
b00000010 +
b0000000001110010 0
b00000010 6
b0000000001110010 ;
b00000010 A
b0000000001110010 F
b00000010 L
b0000000001110010 Q
b00000010 W
b0000000001110010 \
#20000000
1!
1)
14
1?
1J
1U
#21000000
b00000001 #
b00000001 +
b0000000001011001 0
b00000001 6
b0000000001011001 ;
b00000001 A
b0000000001011001 F
b00000001 L
b0000000001011001 Q
b00000001 W
b0000000001011001 \
#22000000
0!
0)
04
0?
0J
0U
#23000000
b00000011 #
b00000001 %
b0000000100000001000000010000000100000001 (
b00000011 +
b00000001 /
b0000000010001011 0
b00000001 1
b00000001 2
b00000011 6
b00000001 :
b0000000010001011 ;
b00000001 <
b00000001 =
b00000011 A
b00000001 E
b0000000010001011 F
b00000001 G
b00000001 H
b00000011 L
b00000001 P
b0000000010001011 Q
b00000001 R
b00000001 S
b00000011 W
b00000001 [
b0000000010001011 \
b00000001 ]
b00000001 ^
#24000000
1!
b00000010 %
b000000010000000100000001000000010000000100000000 &
b0000001000000010000000100000001000000001 (
1)
b00000001 .
b00000001 3
14
b00000001 7
b00000001 9
b00000010 :
b00000010 <
b00000010 =
b00000001 >
1?
b00000001 B
b00000001 D
b00000010 E
b00000010 G
b00000010 H
b00000001 I
1J
b00000001 M
b00000001 O
b00000010 P
b00000010 R
b00000010 S
b00000001 T
1U
b00000001 X
b00000001 Z
b00000010 [
b00000010 ]
b00000010 ^
b00000001 _
#25000000
b00000001 #
b00000001 %
b0000000100000001000000010000000100000000 (
b00000001 +
b00000000 /
b0000000001011001 0
b00000000 1
b00000000 2
b00000001 6
b00000001 :
b0000000001011001 ;
b00000001 <
b00000001 =
b00000001 A
b00000001 E
b0000000001011001 F
b00000001 G
b00000001 H
b00000001 L
b00000001 P
b0000000001011001 Q
b00000001 R
b00000001 S
b00000001 W
b00000001 [
b0000000001011001 \
b00000001 ]
b00000001 ^
#26000000
0!
0)
04
0?
0J
0U
#27000000
b00000011 #
b00000010 %
b0000001000000010000000100000001000000001 (
b00000011 +
b00000001 /
b0000000010001011 0
b00000001 1
b00000001 2
b00000011 6
b00000010 :
b0000000010001011 ;
b00000010 <
b00000010 =
b00000011 A
b00000010 E
b0000000010001011 F
b00000010 G
b00000010 H
b00000011 L
b00000010 P
b0000000010001011 Q
b00000010 R
b00000010 S
b00000011 W
b00000010 [
b0000000010001011 \
b00000010 ]
b00000010 ^
#28000000
1!
b00000011 %
b000000100000001000000010000000100000000100000000 &
b0000001100000011000000110000001000000001 (
1)
14
b00000010 9
b00000010 >
1?
b00000010 B
b00000010 D
b00000011 E
b00000011 G
b00000011 H
b00000010 I
1J
b00000010 M
b00000010 O
b00000011 P
b00000011 R
b00000011 S
b00000010 T
1U
b00000010 X
b00000010 Z
b00000011 [
b00000011 ]
b00000011 ^
b00000010 _
#29000000
b00000010 #
b00000010 %
b0000001000000010000000100000000100000000 (
b00000010 +
b00000000 /
b0000000001110010 0
b00000000 1
b00000000 2
b00000010 6
b00000001 :
b0000000001110010 ;
b00000001 <
b00000001 =
b00000010 A
b00000010 E
b0000000001110010 F
b00000010 G
b00000010 H
b00000010 L
b00000010 P
b0000000001110010 Q
b00000010 R
b00000010 S
b00000010 W
b00000010 [
b0000000001110010 \
b00000010 ]
b00000010 ^
#30000000
0!
0)
04
0?
0J
0U
#31000000
b00000011 #
b00000011 %
b0000001100000011000000110000001000000001 (
b00000011 +
b00000001 /
b0000000010001011 0
b00000001 1
b00000001 2
b00000011 6
b00000010 :
b0000000010001011 ;
b00000010 <
b00000010 =
b00000011 A
b00000011 E
b0000000010001011 F
b00000011 G
b00000011 H
b00000011 L
b00000011 P
b0000000010001011 Q
b00000011 R
b00000011 S
b00000011 W
b00000011 [
b0000000010001011 \
b00000011 ]
b00000011 ^
#32000000
1!
b00000100 %
b000000110000001100000011000000100000000100000000 &
b0000010000000100000000110000001000000001 (
1)
14
1?
b00000011 D
b00000011 I
1J
b00000011 M
b00000011 O
b00000100 P
b00000100 R
b00000100 S
b00000011 T
1U
b00000011 X
b00000011 Z
b00000100 [
b00000100 ]
b00000100 ^
b00000011 _
#33000000
#34000000
0!
0)
04
0?
0J
0U
#35000000
#36000000
1!
b00000101 %
b000001000000010000000011000000100000000100000000 &
b0000010100000100000000110000001000000001 (
1)
14
1?
1J
b00000100 O
b00000100 T
1U
b00000100 X
b00000100 Z
b00000101 [
b00000101 ]
b00000101 ^
b00000100 _
#37000000
b00000100 #
b00000100 +
b0000000010100100 0
b00000100 6
b0000000010100100 ;
b00000100 A
b0000000010100100 F
b00000100 L
b0000000010100100 Q
b00000100 W
b0000000010100100 \
#38000000
0!
0)
04
0?
0J
0U
#39000000
b00000011 #
b00000011 +
b0000000010001011 0
b00000011 6
b0000000010001011 ;
b00000011 A
b0000000010001011 F
b00000011 L
b0000000010001011 Q
b00000011 W
b0000000010001011 \
#40000000
1!
b000001010000010000000011000000100000000100000000 &
1)
14
1?
1J
1U
b00000101 Z
b00000101 _
#41000000
b00000100 #
b00000100 +
b0000000010100100 0
b00000100 6
b0000000010100100 ;
b00000100 A
b0000000010100100 F
b00000100 L
b0000000010100100 Q
b00000100 W
b0000000010100100 \
#42000000
0!
0)
04
0?
0J
0U
#43000000
b00000011 #
b00000011 +
b0000000010001011 0
b00000011 6
b0000000010001011 ;
b00000011 A
b0000000010001011 F
b00000011 L
b0000000010001011 Q
b00000011 W
b0000000010001011 \
#44000000
1!
1)
14
1?
1J
1U
#45000000
b00000101 #
b00000101 +
b0000000010111101 0
b00000101 6
b0000000010111101 ;
b00000101 A
b0000000010111101 F
b00000101 L
b0000000010111101 Q
b00000101 W
b0000000010111101 \
#46000000
0!
0)
04
0?
0J
0U
#47000000
b00000011 #
b00000011 +
b0000000010001011 0
b00000011 6
b0000000010001011 ;
b00000011 A
b0000000010001011 F
b00000011 L
b0000000010001011 Q
b00000011 W
b0000000010001011 \
#48000000
1!
1)
14
1?
1J
1U
#49000000
b00000101 #
b00000101 +
b0000000010111101 0
b00000101 6
b0000000010111101 ;
b00000101 A
b0000000010111101 F
b00000101 L
b0000000010111101 Q
b00000101 W
b0000000010111101 \
#50000000
0!
0)
04
0?
0J
0U
#51000000
b00000011 #
b00000011 +
b0000000010001011 0
b00000011 6
b0000000010001011 ;
b00000011 A
b0000000010001011 F
b00000011 L
b0000000010001011 Q
b00000011 W
b0000000010001011 \
#52000000
1!
1)
14
1?
1J
1U
#53000000
b00000110 #
b00000110 +
b0000000011010110 0
b00000110 6
b0000000011010110 ;
b00000110 A
b0000000011010110 F
b00000110 L
b0000000011010110 Q
b00000110 W
b0000000011010110 \
#54000000
0!
0)
04
0?
0J
0U
#55000000
b00000100 #
b00000100 +
b0000000010100100 0
b00000100 6
b0000000010100100 ;
b00000100 A
b0000000010100100 F
b00000100 L
b0000000010100100 Q
b00000100 W
b0000000010100100 \
#56000000
1!
1)
14
1?
1J
1U
#57000000
b00000110 #
b00000110 +
b0000000011010110 0
b00000110 6
b0000000011010110 ;
b00000110 A
b0000000011010110 F
b00000110 L
b0000000011010110 Q
b00000110 W
b0000000011010110 \
#58000000
0!
0)
04
0?
0J
0U
#59000000
b00000100 #
b00000100 +
b0000000010100100 0
b00000100 6
b0000000010100100 ;
b00000100 A
b0000000010100100 F
b00000100 L
b0000000010100100 Q
b00000100 W
b0000000010100100 \
#60000000
1!
1)
14
1?
1J
1U
#61000000
b00000110 #
b00000110 +
b0000000011010110 0
b00000110 6
b0000000011010110 ;
b00000110 A
b0000000011010110 F
b00000110 L
b0000000011010110 Q
b00000110 W
b0000000011010110 \
#62000000
0!
0)
04
0?
0J
0U
#63000000
b00000101 #
b00000101 +
b0000000010111101 0
b00000101 6
b0000000010111101 ;
b00000101 A
b0000000010111101 F
b00000101 L
b0000000010111101 Q
b00000101 W
b0000000010111101 \
#64000000
1!
1)
14
1?
1J
1U
#65000000
b00000110 #
b00000110 +
b0000000011010110 0
b00000110 6
b0000000011010110 ;
b00000110 A
b0000000011010110 F
b00000110 L
b0000000011010110 Q
b00000110 W
b0000000011010110 \
#66000000
0!
0)
04
0?
0J
0U
#67000000
b00000101 #
b00000101 +
b0000000010111101 0
b00000101 6
b0000000010111101 ;
b00000101 A
b0000000010111101 F
b00000101 L
b0000000010111101 Q
b00000101 W
b0000000010111101 \
#68000000
1!
1)
14
1?
1J
1U
#69000000
b00000110 #
b00000110 +
b0000000011010110 0
b00000110 6
b0000000011010110 ;
b00000110 A
b0000000011010110 F
b00000110 L
b0000000011010110 Q
b00000110 W
b0000000011010110 \
#70000000
0!
0)
04
0?
0J
0U
#71000000
#72000000
1!
1)
14
1?
1J
1U
#73000000
b00000101 #
b00000101 +
b0000000010111101 0
b00000101 6
b0000000010111101 ;
b00000101 A
b0000000010111101 F
b00000101 L
b0000000010111101 Q
b00000101 W
b0000000010111101 \
#74000000
0!
0)
04
0?
0J
0U
#75000000
b00000111 #
b00000111 +
b0000000011101111 0
b00000111 6
b0000000011101111 ;
b00000111 A
b0000000011101111 F
b00000111 L
b0000000011101111 Q
b00000111 W
b0000000011101111 \
#76000000
1!
1)
14
1?
1J
1U
#77000000
b00000101 #
b00000101 +
b0000000010111101 0
b00000101 6
b0000000010111101 ;
b00000101 A
b0000000010111101 F
b00000101 L
b0000000010111101 Q
b00000101 W
b0000000010111101 \
#78000000
0!
0)
04
0?
0J
0U
#79000000
b00000111 #
b00000111 +
b0000000011101111 0
b00000111 6
b0000000011101111 ;
b00000111 A
b0000000011101111 F
b00000111 L
b0000000011101111 Q
b00000111 W
b0000000011101111 \
#80000000
1!
1)
14
1?
1J
1U
#81000000
b00000101 #
b00000101 +
b0000000010111101 0
b00000101 6
b0000000010111101 ;
b00000101 A
b0000000010111101 F
b00000101 L
b0000000010111101 Q
b00000101 W
b0000000010111101 \
#82000000
0!
0)
04
0?
0J
0U
#83000000
b00000111 #
b00000111 +
b0000000011101111 0
b00000111 6
b0000000011101111 ;
b00000111 A
b0000000011101111 F
b00000111 L
b0000000011101111 Q
b00000111 W
b0000000011101111 \
#84000000
1!
1)
14
1?
1J
1U
#85000000
b00000101 #
b00000101 +
b0000000010111101 0
b00000101 6
b0000000010111101 ;
b00000101 A
b0000000010111101 F
b00000101 L
b0000000010111101 Q
b00000101 W
b0000000010111101 \
#86000000
0!
0)
04
0?
0J
0U
#87000000
b00000111 #
b00000111 +
b0000000011101111 0
b00000111 6
b0000000011101111 ;
b00000111 A
b0000000011101111 F
b00000111 L
b0000000011101111 Q
b00000111 W
b0000000011101111 \
#88000000
1!
1)
14
1?
1J
1U
#89000000
b00000101 #
b00000101 +
b0000000010111101 0
b00000101 6
b0000000010111101 ;
b00000101 A
b0000000010111101 F
b00000101 L
b0000000010111101 Q
b00000101 W
b0000000010111101 \
#90000000
0!
0)
04
0?
0J
0U
#91000000
b00000111 #
b00000111 +
b0000000011101111 0
b00000111 6
b0000000011101111 ;
b00000111 A
b0000000011101111 F
b00000111 L
b0000000011101111 Q
b00000111 W
b0000000011101111 \
#92000000
1!
1)
14
1?
1J
1U
#93000000
b00000110 #
b00000110 +
b0000000011010110 0
b00000110 6
b0000000011010110 ;
b00000110 A
b0000000011010110 F
b00000110 L
b0000000011010110 Q
b00000110 W
b0000000011010110 \
#94000000
0!
0)
04
0?
0J
0U
#95000000
b00000111 #
b00000111 +
b0000000011101111 0
b00000111 6
b0000000011101111 ;
b00000111 A
b0000000011101111 F
b00000111 L
b0000000011101111 Q
b00000111 W
b0000000011101111 \
#96000000
1!
1)
14
1?
1J
1U
#97000000
b00000110 #
b00000110 +
b0000000011010110 0
b00000110 6
b0000000011010110 ;
b00000110 A
b0000000011010110 F
b00000110 L
b0000000011010110 Q
b00000110 W
b0000000011010110 \
#98000000
0!
0)
04
0?
0J
0U
#99000000
b00000111 #
b00000111 +
b0000000011101111 0
b00000111 6
b0000000011101111 ;
b00000111 A
b0000000011101111 F
b00000111 L
b0000000011101111 Q
b00000111 W
b0000000011101111 \
#100000000
1!
1)
14
1?
1J
1U
#101000000
b00000110 #
b00000110 +
b0000000011010110 0
b00000110 6
b0000000011010110 ;
b00000110 A
b0000000011010110 F
b00000110 L
b0000000011010110 Q
b00000110 W
b0000000011010110 \
#102000000
0!
0)
04
0?
0J
0U
#103000000
#104000000
1!
1)
14
1?
1J
1U
#105000000
b00000111 #
b00000111 +
b0000000011101111 0
b00000111 6
b0000000011101111 ;
b00000111 A
b0000000011101111 F
b00000111 L
b0000000011101111 Q
b00000111 W
b0000000011101111 \
#106000000
0!
0)
04
0?
0J
0U
#107000000
b00000110 #
b00000110 +
b0000000011010110 0
b00000110 6
b0000000011010110 ;
b00000110 A
b0000000011010110 F
b00000110 L
b0000000011010110 Q
b00000110 W
b0000000011010110 \
#108000000
1!
1)
14
1?
1J
1U
#109000000
b00000111 #
b00000111 +
b0000000011101111 0
b00000111 6
b0000000011101111 ;
b00000111 A
b0000000011101111 F
b00000111 L
b0000000011101111 Q
b00000111 W
b0000000011101111 \
#110000000
0!
0)
04
0?
0J
0U
#111000000
b00000110 #
b00000110 +
b0000000011010110 0
b00000110 6
b0000000011010110 ;
b00000110 A
b0000000011010110 F
b00000110 L
b0000000011010110 Q
b00000110 W
b0000000011010110 \
#112000000
1!
1)
14
1?
1J
1U
#113000000
b00000111 #
b00000111 +
b0000000011101111 0
b00000111 6
b0000000011101111 ;
b00000111 A
b0000000011101111 F
b00000111 L
b0000000011101111 Q
b00000111 W
b0000000011101111 \
#114000000
0!
0)
04
0?
0J
0U
#115000000
b00000101 #
b00000101 +
b0000000010111101 0
b00000101 6
b0000000010111101 ;
b00000101 A
b0000000010111101 F
b00000101 L
b0000000010111101 Q
b00000101 W
b0000000010111101 \
#116000000
1!
1)
14
1?
1J
1U
#117000000
b00000111 #
b00000111 +
b0000000011101111 0
b00000111 6
b0000000011101111 ;
b00000111 A
b0000000011101111 F
b00000111 L
b0000000011101111 Q
b00000111 W
b0000000011101111 \
#118000000
0!
0)
04
0?
0J
0U
#119000000
b00000101 #
b00000101 +
b0000000010111101 0
b00000101 6
b0000000010111101 ;
b00000101 A
b0000000010111101 F
b00000101 L
b0000000010111101 Q
b00000101 W
b0000000010111101 \
#120000000
1!
1)
14
1?
1J
1U
#121000000
b00000111 #
b00000111 +
b0000000011101111 0
b00000111 6
b0000000011101111 ;
b00000111 A
b0000000011101111 F
b00000111 L
b0000000011101111 Q
b00000111 W
b0000000011101111 \
#122000000
0!
0)
04
0?
0J
0U
#123000000
b00000101 #
b00000101 +
b0000000010111101 0
b00000101 6
b0000000010111101 ;
b00000101 A
b0000000010111101 F
b00000101 L
b0000000010111101 Q
b00000101 W
b0000000010111101 \
#124000000
1!
1)
14
1?
1J
1U
#125000000
b00000111 #
b00000111 +
b0000000011101111 0
b00000111 6
b0000000011101111 ;
b00000111 A
b0000000011101111 F
b00000111 L
b0000000011101111 Q
b00000111 W
b0000000011101111 \
#126000000
0!
0)
04
0?
0J
0U
#127000000
b00000101 #
b00000101 +
b0000000010111101 0
b00000101 6
b0000000010111101 ;
b00000101 A
b0000000010111101 F
b00000101 L
b0000000010111101 Q
b00000101 W
b0000000010111101 \
#128000000
1!
1)
14
1?
1J
1U
#129000000
b00000110 #
b00000110 +
b0000000011010110 0
b00000110 6
b0000000011010110 ;
b00000110 A
b0000000011010110 F
b00000110 L
b0000000011010110 Q
b00000110 W
b0000000011010110 \
#130000000
0!
0)
04
0?
0J
0U
#131000000
b00000101 #
b00000101 +
b0000000010111101 0
b00000101 6
b0000000010111101 ;
b00000101 A
b0000000010111101 F
b00000101 L
b0000000010111101 Q
b00000101 W
b0000000010111101 \
#132000000
1!
1)
14
1?
1J
1U
#133000000
b00000110 #
b00000110 +
b0000000011010110 0
b00000110 6
b0000000011010110 ;
b00000110 A
b0000000011010110 F
b00000110 L
b0000000011010110 Q
b00000110 W
b0000000011010110 \
#134000000
0!
0)
04
0?
0J
0U
#135000000
#136000000
1!
1)
14
1?
1J
1U
#137000000
b00000101 #
b00000101 +
b0000000010111101 0
b00000101 6
b0000000010111101 ;
b00000101 A
b0000000010111101 F
b00000101 L
b0000000010111101 Q
b00000101 W
b0000000010111101 \
#138000000
0!
0)
04
0?
0J
0U
#139000000
b00000110 #
b00000110 +
b0000000011010110 0
b00000110 6
b0000000011010110 ;
b00000110 A
b0000000011010110 F
b00000110 L
b0000000011010110 Q
b00000110 W
b0000000011010110 \
#140000000
1!
1)
14
1?
1J
1U
#141000000
b00000101 #
b00000101 +
b0000000010111101 0
b00000101 6
b0000000010111101 ;
b00000101 A
b0000000010111101 F
b00000101 L
b0000000010111101 Q
b00000101 W
b0000000010111101 \
#142000000
0!
0)
04
0?
0J
0U
#143000000
b00000110 #
b00000110 +
b0000000011010110 0
b00000110 6
b0000000011010110 ;
b00000110 A
b0000000011010110 F
b00000110 L
b0000000011010110 Q
b00000110 W
b0000000011010110 \
#144000000
1!
1)
14
1?
1J
1U
#145000000
b00000100 #
b00000100 +
b0000000010100100 0
b00000100 6
b0000000010100100 ;
b00000100 A
b0000000010100100 F
b00000100 L
b0000000010100100 Q
b00000100 W
b0000000010100100 \
#146000000
0!
0)
04
0?
0J
0U
#147000000
b00000110 #
b00000110 +
b0000000011010110 0
b00000110 6
b0000000011010110 ;
b00000110 A
b0000000011010110 F
b00000110 L
b0000000011010110 Q
b00000110 W
b0000000011010110 \
#148000000
1!
1)
14
1?
1J
1U
#149000000
b00000100 #
b00000100 +
b0000000010100100 0
b00000100 6
b0000000010100100 ;
b00000100 A
b0000000010100100 F
b00000100 L
b0000000010100100 Q
b00000100 W
b0000000010100100 \
#150000000
0!
0)
04
0?
0J
0U
#151000000
b00000101 #
b00000101 +
b0000000010111101 0
b00000101 6
b0000000010111101 ;
b00000101 A
b0000000010111101 F
b00000101 L
b0000000010111101 Q
b00000101 W
b0000000010111101 \
#152000000
1!
1)
14
1?
1J
1U
#153000000
b00000011 #
b00000011 +
b0000000010001011 0
b00000011 6
b0000000010001011 ;
b00000011 A
b0000000010001011 F
b00000011 L
b0000000010001011 Q
b00000011 W
b0000000010001011 \
#154000000
0!
0)
04
0?
0J
0U
#155000000
b00000101 #
b00000101 +
b0000000010111101 0
b00000101 6
b0000000010111101 ;
b00000101 A
b0000000010111101 F
b00000101 L
b0000000010111101 Q
b00000101 W
b0000000010111101 \
#156000000
1!
1)
14
1?
1J
1U
#157000000
b00000011 #
b00000011 +
b0000000010001011 0
b00000011 6
b0000000010001011 ;
b00000011 A
b0000000010001011 F
b00000011 L
b0000000010001011 Q
b00000011 W
b0000000010001011 \
#158000000
0!
0)
04
0?
0J
0U
#159000000
b00000101 #
b00000101 +
b0000000010111101 0
b00000101 6
b0000000010111101 ;
b00000101 A
b0000000010111101 F
b00000101 L
b0000000010111101 Q
b00000101 W
b0000000010111101 \
#160000000
1!
1)
14
1?
1J
1U
#161000000
b00000011 #
b00000011 +
b0000000010001011 0
b00000011 6
b0000000010001011 ;
b00000011 A
b0000000010001011 F
b00000011 L
b0000000010001011 Q
b00000011 W
b0000000010001011 \
#162000000
0!
0)
04
0?
0J
0U
#163000000
b00000100 #
b00000100 +
b0000000010100100 0
b00000100 6
b0000000010100100 ;
b00000100 A
b0000000010100100 F
b00000100 L
b0000000010100100 Q
b00000100 W
b0000000010100100 \
#164000000
1!
1)
14
1?
1J
1U
